LICENSE
MANIFEST.in
README.rst
requirements.txt
setup.py
Flask_Turbo_Boost.egg-info/PKG-INFO
Flask_Turbo_Boost.egg-info/SOURCES.txt
Flask_Turbo_Boost.egg-info/dependency_links.txt
Flask_Turbo_Boost.egg-info/entry_points.txt
Flask_Turbo_Boost.egg-info/requires.txt
Flask_Turbo_Boost.egg-info/top_level.txt
flask_turbo_boost/__init__.py
flask_turbo_boost/cli.py
flask_turbo_boost/api_project/.flaskenv
flask_turbo_boost/api_project/.gitignore
flask_turbo_boost/api_project/Dockerfile
flask_turbo_boost/api_project/README.md
flask_turbo_boost/api_project/docker-compose.yml
flask_turbo_boost/api_project/fabfile.py
flask_turbo_boost/api_project/pylintrc
flask_turbo_boost/api_project/requirements.txt
flask_turbo_boost/api_project/wsgi.py
flask_turbo_boost/api_project/application/__init__.py
flask_turbo_boost/api_project/application/controllers/__init__.py
flask_turbo_boost/api_project/application/controllers/site.py
flask_turbo_boost/api_project/application/controllers/api_v1/__init__.py
flask_turbo_boost/api_project/application/controllers/api_v1/users.py
flask_turbo_boost/api_project/application/extensions/active_record_mixin.py
flask_turbo_boost/api_project/application/extensions/json_validator.py
flask_turbo_boost/api_project/application/extensions/jwt_auth.py
flask_turbo_boost/api_project/application/extensions/searchable_mixin.py
flask_turbo_boost/api_project/application/forms/__init__.py
flask_turbo_boost/api_project/application/forms/_helper.py
flask_turbo_boost/api_project/application/forms/account.py
flask_turbo_boost/api_project/application/models/__init__.py
flask_turbo_boost/api_project/application/models/_base.py
flask_turbo_boost/api_project/application/models/role.py
flask_turbo_boost/api_project/application/models/user.py
flask_turbo_boost/api_project/application/models/work_flow.py
flask_turbo_boost/api_project/application/models/work_flow_instance.py
flask_turbo_boost/api_project/application/models/work_flow_instance_detail.py
flask_turbo_boost/api_project/application/models/work_flow_state.py
flask_turbo_boost/api_project/application/models/work_flow_transition.py
flask_turbo_boost/api_project/application/utils/__init__.py
flask_turbo_boost/api_project/application/utils/account.py
