Metadata-Version: 1.1
Name: Flask-Turbo-Boost
Version: 0.2.7
Summary: Forked Flask-Boost - Flask application generator for boosting your development.
Home-page: https://github.com/jingz/Flask-Boost
Author: jingz
Author-email: wsaryoo@gmail.com
License: MIT
Keywords: flask project template rich-sample generator
Platform: UNKNOWN
Classifier: Development Status :: 4 - Beta
Classifier: Environment :: Web Environment
Classifier: Intended Audience :: Developers
Classifier: License :: OSI Approved :: MIT License
Classifier: Operating System :: OS Independent
Classifier: Programming Language :: Python
Classifier: Programming Language :: Python :: 3
Classifier: Programming Language :: Python :: 3.7
Classifier: Topic :: Internet :: WWW/HTTP :: Dynamic Content
Classifier: Topic :: Internet :: WWW/HTTP :: WSGI
Classifier: Topic :: Software Development :: Libraries :: Application Frameworks
Classifier: Topic :: Software Development :: Libraries :: Python Modules
